MANIFEST.in
README.md
setup.cfg
setup.py
versioneer.py
ParmEd.egg-info/PKG-INFO
ParmEd.egg-info/SOURCES.txt
ParmEd.egg-info/dependency_links.txt
ParmEd.egg-info/entry_points.txt
ParmEd.egg-info/top_level.txt
examples/amber/ala2_solv.parm7
examples/amber/ala2_solv.rst7
examples/amber/ala5_gas.parm7
examples/amber/ala5_gas.rst7
examples/amber/simulate_amber_gb.py
examples/amber/simulate_amber_pme.py
examples/charmm/ala2_charmmgui.crd
examples/charmm/ala2_charmmgui.psf
examples/charmm/ala5_autopsf.pdb
examples/charmm/ala5_autopsf.psf
examples/charmm/simulate_charmm_gb.py
examples/charmm/simulate_charmm_gui.py
examples/charmm/toppar/par_all36_prot.prm
examples/charmm/toppar/toppar_water_ions.str
examples/gromacs/dhfr_gas.gro
examples/gromacs/dhfr_gas.top
examples/gromacs/dhfr_pme.gro
examples/gromacs/dhfr_pme.top
examples/gromacs/simulate_gromacs_gb.py
examples/gromacs/simulate_gromacs_pme.py
examples/rosetta/simulate_ala12_mutant.py
parmed/__init__.py
parmed/_version.py
parmed/constants.py
parmed/exceptions.py
parmed/geometry.py
parmed/parameters.py
parmed/periodic_table.py
parmed/residue.py
parmed/scripts.py
parmed/structure.py
parmed/symmetry.py
parmed/topologyobjects.py
parmed/vec3.py
parmed/__pycache__/__init__.cpython-310.pyc
parmed/__pycache__/__init__.cpython-39.pyc
parmed/__pycache__/__init__.pypy39.pyc
parmed/__pycache__/_version.cpython-310.pyc
parmed/__pycache__/_version.cpython-39.pyc
parmed/__pycache__/_version.pypy39.pyc
parmed/__pycache__/constants.cpython-310.pyc
parmed/__pycache__/constants.cpython-39.pyc
parmed/__pycache__/constants.pypy39.pyc
parmed/__pycache__/exceptions.cpython-310.pyc
parmed/__pycache__/exceptions.cpython-39.pyc
parmed/__pycache__/exceptions.pypy39.pyc
parmed/__pycache__/geometry.cpython-310.pyc
parmed/__pycache__/geometry.cpython-39.pyc
parmed/__pycache__/geometry.pypy39.pyc
parmed/__pycache__/parameters.cpython-310.pyc
parmed/__pycache__/parameters.cpython-39.pyc
parmed/__pycache__/parameters.pypy39.pyc
parmed/__pycache__/periodic_table.cpython-310.pyc
parmed/__pycache__/periodic_table.cpython-39.pyc
parmed/__pycache__/periodic_table.pypy39.pyc
