Metadata-Version: 2.1
Name: ParmEd
Version: 4.2.1
Summary: Inter-package toolkit for molecular mechanical simulations
Home-page: https://parmed.github.io/ParmEd/html/index.html
Author: Jason Swails
Author-email: jason.swails@gmail.com
License: LGPL
Requires-Python: >=3.8
